apigee/__init__.py
apigee/__main__.py
apigee/auth.py
apigee/cls.py
apigee/console.py
apigee/crypto.py
apigee/encryption_utils.py
apigee/exceptions.py
apigee/prefix.py
apigee/silent.py
apigee/types.py
apigee/utils.py
apigee/utils_init.py
apigee/verbose.py
apigee/apiproducts/__init__.py
apigee/apiproducts/apiproducts.py
apigee/apiproducts/commands.py
apigee/apiproducts/serializer.py
apigee/apis/__init__.py
apigee/apis/api_puller_with_dependency_extraction.py
apigee/apis/apis.py
apigee/apis/commands.py
apigee/apis/deploy.py
apigee/apis/pull.py
apigee/apis/serializer.py
apigee/apps/__init__.py
apigee/apps/apps.py
apigee/apps/commands.py
apigee/apps/serializer.py
apigee/backups/__init__.py
apigee/backups/backups.py
apigee/backups/commands.py
apigee/caches/__init__.py
apigee/caches/caches.py
apigee/caches/commands.py
apigee/caches/serializer.py
apigee/configure/__init__.py
apigee/configure/commands.py
apigee/deployments/__init__.py
apigee/deployments/commands.py
apigee/deployments/deployments.py
apigee/deployments/serializer.py
apigee/developers/__init__.py
apigee/developers/commands.py
apigee/developers/developers.py
apigee/developers/serializer.py
apigee/keystores/__init__.py
apigee/keystores/commands.py
apigee/keystores/keystores.py
apigee/keystores/serializer.py
apigee/keyvaluemaps/__init__.py
apigee/keyvaluemaps/commands.py
apigee/keyvaluemaps/keyvaluemaps.py
apigee/keyvaluemaps/serializer.py
apigee/maskconfigs/__init__.py
apigee/maskconfigs/commands.py
apigee/maskconfigs/maskconfigs.py
apigee/maskconfigs/serializer.py
apigee/permissions/__init__.py
apigee/permissions/commands.py
apigee/permissions/permissions.py
apigee/permissions/serializer.py
apigee/plugins/__init__.py
apigee/plugins/commands.py
apigee/references/__init__.py
apigee/references/commands.py
apigee/references/references.py
apigee/references/serializer.py
apigee/sharedflows/__init__.py
apigee/sharedflows/commands.py
apigee/sharedflows/serializer.py
apigee/sharedflows/sharedflows.py
apigeecli-0.53.11.dist-info/LICENSE
apigeecli-0.53.11.dist-info/METADATA
apigeecli-0.53.11.dist-info/NOTICE
apigeecli-0.53.11.dist-info/WHEEL
apigeecli-0.53.11.dist-info/entry_points.txt
apigeecli-0.53.11.dist-info/top_level.txt
apigeecli-0.53.11.dist-info/RECORD
