Metadata-Version: 2.1
Name: apigeecli
Version: 0.53.11
Summary: (DEPRECATED) apigeecli simplifies and automates Apigee Edge API usage.
Home-page: https://github.com/darumatic/apigee-cli
Author: Matthew Delotavo
Author-email: matthew.t.delotavo@gmail.com
License: Apache license 2.0
Project-URL: Documentation, https://darumatic.github.io/apigee-cli/index.html
Platform: UNKNOWN
Classifier: Development Status :: 4 - Beta
Classifier: Environment :: Console
Classifier: Intended Audience :: Developers
Classifier: License :: OSI Approved :: Apache Software License
Classifier: Operating System :: OS Independent
Classifier: Programming Language :: Python :: 3.7
Requires-Python: >=3.7
License-File: LICENSE
License-File: NOTICE
Requires-Dist: GitPython>=3.1.34
Requires-Dist: PyJWT>=2.6.0
Requires-Dist: click-aliases>=1.0.1
Requires-Dist: click-option-group>=0.5.5
Requires-Dist: click>=8.1.3
Requires-Dist: colorama>=0.4.6
Requires-Dist: pyotp>=2.8.0
Requires-Dist: python-gnupg>=0.3.5
Requires-Dist: requests>=2.31.0
Requires-Dist: tabulate>=0.9.0
Requires-Dist: tqdm>=4.64.1
